{
  "version": "6.0",
  "nxVersion": "21.1.3",
  "pathMappings": {
    "@frontend-templates/eslint-config": [
      "packages/eslint-config/index.js"
    ],
    "@frontend-templates/prettier-config": [
      "packages/prettier-config/index.js"
    ],
    "@frontend-templates/tsconfig": [
      "packages/tsconfig/index.js"
    ]
  },
  "nxJsonPlugins": [
    {
      "name": "@nx/next/plugin",
      "options": {
        "startTargetName": "start",
        "buildTargetName": "build",
        "devTargetName": "dev",
        "serveStaticTargetName": "serve-static"
      }
    }
  ],
  "fileMap": {
    "projectFileMap": {
      "eslint-config": [
        {
          "file": "packages/eslint-config/index.js",
          "hash": "2257672257858404718",
          "deps": [
            "npm:@eslint/compat",
            "npm:@eslint/eslintrc",
            "npm:@eslint/js@9.28.0",
            "npm:@typescript-eslint/eslint-plugin",
            "npm:@typescript-eslint/parser",
            "npm:eslint-plugin-import",
            "npm:eslint-plugin-jest",
            "npm:eslint-plugin-jsx-a11y",
            "npm:eslint-plugin-playwright",
            "npm:eslint-plugin-react",
            "npm:eslint-plugin-react-hooks",
            "npm:eslint-plugin-testing-library",
            "npm:globals@16.2.0"
          ]
        },
        {
          "file": "packages/eslint-config/package.json",
          "hash": "5730075912351835032",
          "deps": [
            "npm:eslint@9.28.0",
            "npm:typescript",
            "npm:@eslint/compat",
            "npm:@eslint/eslintrc",
            "npm:@eslint/js@9.28.0",
            "npm:@typescript-eslint/eslint-plugin",
            "npm:@typescript-eslint/parser",
            "npm:eslint-config-prettier",
            "npm:eslint-plugin-import",
            "npm:eslint-plugin-jest",
            "npm:eslint-plugin-jsx-a11y",
            "npm:eslint-plugin-playwright",
            "npm:eslint-plugin-prettier",
            "npm:eslint-plugin-react",
            "npm:eslint-plugin-react-hooks",
            "npm:eslint-plugin-testing-library",
            "npm:globals@16.2.0"
          ]
        },
        {
          "file": "packages/eslint-config/project.json",
          "hash": "12720190802872368598"
        }
      ],
      "prettier-config": [
        {
          "file": "packages/prettier-config/index.js",
          "hash": "3715958894174302135"
        },
        {
          "file": "packages/prettier-config/package.json",
          "hash": "6871353547823440277",
          "deps": [
            "npm:prettier@3.5.3"
          ]
        },
        {
          "file": "packages/prettier-config/project.json",
          "hash": "15179603704991308780"
        }
      ],
      "tsconfig": [
        {
          "file": "packages/tsconfig/base.json",
          "hash": "7277492661227644211"
        },
        {
          "file": "packages/tsconfig/index.js",
          "hash": "1769695778783855813"
        },
        {
          "file": "packages/tsconfig/nextjs.json",
          "hash": "5356433211710566610"
        },
        {
          "file": "packages/tsconfig/package.json",
          "hash": "8089998542254419152",
          "deps": [
            "npm:typescript"
          ]
        },
        {
          "file": "packages/tsconfig/project.json",
          "hash": "10688360124300095934"
        },
        {
          "file": "packages/tsconfig/react-router.json",
          "hash": "1563624985163608748"
        }
      ],
      "react-template-next": [
        {
          "file": "apps/react-template-next/.env.sample",
          "hash": "11778743402755738376"
        },
        {
          "file": "apps/react-template-next/.github/issue_template.md",
          "hash": "10395249463968647000"
        },
        {
          "file": "apps/react-template-next/.github/pull_request_template.md",
          "hash": "17709958282604071433"
        },
        {
          "file": "apps/react-template-next/.github/workflows/ci_cd.yml",
          "hash": "5878850679542105345"
        },
        {
          "file": "apps/react-template-next/.github/workflows/dependencies_update.yml",
          "hash": "16553150589125657534"
        },
        {
          "file": "apps/react-template-next/.gitignore",
          "hash": "4898746511972444573"
        },
        {
          "file": "apps/react-template-next/.husky/pre-commit",
          "hash": "3455426949109039222"
        },
        {
          "file": "apps/react-template-next/.lintstagedrc.js",
          "hash": "84872462262408638"
        },
        {
          "file": "apps/react-template-next/.prettierignore",
          "hash": "3800003032039817628"
        },
        {
          "file": "apps/react-template-next/.prettierrc.js",
          "hash": "347793396474411554",
          "deps": [
            "prettier-config"
          ]
        },
        {
          "file": "apps/react-template-next/LICENSE.md",
          "hash": "9160496680738198191"
        },
        {
          "file": "apps/react-template-next/README.md",
          "hash": "2817341369016366674"
        },
        {
          "file": "apps/react-template-next/app/api/healthcheck/route.ts",
          "hash": "3161066698941652750"
        },
        {
          "file": "apps/react-template-next/app/components/global-providers/global-providers.tsx",
          "hash": "2140447522071248028",
          "deps": [
            "npm:@tanstack/react-query",
            "npm:@tanstack/react-query-devtools",
            "npm:next-themes",
            "npm:react@19.1.0"
          ]
        },
        {
          "file": "apps/react-template-next/app/components/theme-switch/theme-switch.test.tsx",
          "hash": "1780300191389906807",
          "deps": [
            "npm:@testing-library/react",
            "npm:@testing-library/user-event"
          ]
        },
        {
          "file": "apps/react-template-next/app/components/theme-switch/theme-switch.tsx",
          "hash": "4162928112718857635",
          "deps": [
            "npm:lucide-react@0.513.0",
            "npm:next-themes",
            "npm:react@19.1.0"
          ]
        },
        {
          "file": "apps/react-template-next/app/components/viewport-info/viewport-info.test.tsx",
          "hash": "14547469001059418828",
          "deps": [
            "npm:@testing-library/react"
          ]
        },
        {
          "file": "apps/react-template-next/app/components/viewport-info/viewport-info.tsx",
          "hash": "14782707485184149745",
          "deps": [
            "npm:lucide-react@0.513.0",
            "npm:react@19.1.0"
          ]
        },
        {
          "file": "apps/react-template-next/app/error.tsx",
          "hash": "10979123689464661062",
          "deps": [
            "npm:react@19.1.0"
          ]
        },
        {
          "file": "apps/react-template-next/app/favicon.ico",
          "hash": "9157999678830540297"
        },
        {
          "file": "apps/react-template-next/app/global-error.tsx",
          "hash": "6365994489472574413",
          "deps": [
            "npm:react@19.1.0"
          ]
        },
        {
          "file": "apps/react-template-next/app/layout.tsx",
          "hash": "13561691351849247504",
          "deps": [
            "npm:next@15.3.3"
          ]
        },
        {
          "file": "apps/react-template-next/app/lib/hooks/useHealthcheck.ts",
          "hash": "1562942126583728466",
          "deps": [
            "npm:@tanstack/react-query"
          ]
        },
        {
          "file": "apps/react-template-next/app/lib/misc/environment.ts",
          "hash": "13876459938821171911"
        },
        {
          "file": "apps/react-template-next/app/lib/misc/react-query.ts",
          "hash": "17229103199200275795",
          "deps": [
            "npm:@tanstack/react-query"
          ]
        },
        {
          "file": "apps/react-template-next/app/lib/mocks/browser.ts",
          "hash": "3743954764170051811",
          "deps": [
            "npm:msw"
          ]
        },
        {
          "file": "apps/react-template-next/app/lib/mocks/handlers.ts",
          "hash": "8565694663020694550",
          "deps": [
            "npm:msw"
          ]
        },
        {
          "file": "apps/react-template-next/app/lib/mocks/index.ts",
          "hash": "12229025000870170582"
        },
        {
          "file": "apps/react-template-next/app/lib/mocks/node.ts",
          "hash": "11959845792427069976",
          "deps": [
            "npm:msw"
          ]
        },
        {
          "file": "apps/react-template-next/app/lib/styles/globals.css",
          "hash": "4678732707632597980"
        },
        {
          "file": "apps/react-template-next/app/not-found.tsx",
          "hash": "7649055626598375851",
          "deps": [
            "npm:lucide-react@0.513.0",
            "npm:next@15.3.3"
          ]
        },
        {
          "file": "apps/react-template-next/app/page.tsx",
          "hash": "1748122237982795029",
          "deps": [
            "npm:lucide-react@0.513.0",
            "npm:next@15.3.3"
          ]
        },
        {
          "file": "apps/react-template-next/app/robots.ts",
          "hash": "6082055634085553465",
          "deps": [
            "npm:next@15.3.3"
          ]
        },
        {
          "file": "apps/react-template-next/app/sitemap.ts",
          "hash": "6396619950971688821",
          "deps": [
            "npm:next@15.3.3"
          ]
        },
        {
          "file": "apps/react-template-next/e2e/index.spec.ts",
          "hash": "5852263184985715543",
          "deps": [
            "npm:@playwright/test"
          ]
        },
        {
          "file": "apps/react-template-next/eslint.config.mjs",
          "hash": "1090339887357754487",
          "deps": [
            "eslint-config"
          ]
        },
        {
          "file": "apps/react-template-next/jest.config.js",
          "hash": "670287854602380622",
          "deps": [
            "npm:next@15.3.3"
          ]
        },
        {
          "file": "apps/react-template-next/jest.setup.js",
          "hash": "18244793749264894043",
          "deps": [
            "npm:@testing-library/jest-dom"
          ]
        },
        {
          "file": "apps/react-template-next/next-env.d.ts",
          "hash": "1320675027584673186"
        },
        {
          "file": "apps/react-template-next/next.config.ts",
          "hash": "3097927344448485179",
          "deps": [
            "npm:next@15.3.3"
          ]
        },
        {
          "file": "apps/react-template-next/package.json",
          "hash": "16823934617274377154",
          "deps": [
            "npm:@eslint/compat",
            "npm:@eslint/eslintrc",
            "npm:@eslint/js@9.28.0",
            "eslint-config",
            "prettier-config",
            "tsconfig",
            "npm:@next/eslint-plugin-next",
            "npm:@playwright/test",
            "npm:@tailwindcss/postcss",
            "npm:@testing-library/dom",
            "npm:@testing-library/jest-dom",
            "npm:@testing-library/react",
            "npm:@testing-library/user-event",
            "npm:@types/jest",
            "npm:@types/node",
            "npm:@types/react",
            "npm:@types/react-dom",
            "npm:@typescript-eslint/eslint-plugin",
            "npm:@typescript-eslint/parser",
            "npm:concurrently",
            "npm:eslint@9.28.0",
            "npm:eslint-config-next",
            "npm:eslint-config-prettier",
            "npm:eslint-plugin-import",
            "npm:eslint-plugin-jest",
            "npm:eslint-plugin-jsx-a11y",
            "npm:eslint-plugin-playwright",
            "npm:eslint-plugin-prettier",
            "npm:eslint-plugin-tailwindcss",
            "npm:eslint-plugin-testing-library",
            "npm:husky",
            "npm:jest",
            "npm:jest-environment-jsdom",
            "npm:lint-staged@16.1.0",
            "npm:msw",
            "npm:postcss@8.5.4",
            "npm:prettier@3.5.3",
            "npm:prettier-plugin-tailwindcss",
            "npm:tailwindcss",
            "npm:typescript",
            "npm:@tanstack/react-query",
            "npm:@tanstack/react-query-devtools",
            "npm:client-only",
            "npm:clsx",
            "npm:lucide-react@0.513.0",
            "npm:next@15.3.3",
            "npm:next-themes",
            "npm:react@19.1.0",
            "npm:react-dom@19.1.0",
            "npm:server-only"
          ]
        },
        {
          "file": "apps/react-template-next/playwright.config.ts",
          "hash": "9676789320082473423",
          "deps": [
            "npm:@playwright/test"
          ]
        },
        {
          "file": "apps/react-template-next/pnpm-lock.yaml",
          "hash": "1317705732590971523"
        },
        {
          "file": "apps/react-template-next/postcss.config.js",
          "hash": "290008532163141866"
        },
        {
          "file": "apps/react-template-next/project.json",
          "hash": "17451668834042914025"
        },
        {
          "file": "apps/react-template-next/public/mockServiceWorker.js",
          "hash": "10072252072268502416"
        },
        {
          "file": "apps/react-template-next/tsconfig.json",
          "hash": "1694444232884936391"
        },
        {
          "file": "apps/react-template-next/vercel.json",
          "hash": "15535816575235842323"
        }
      ],
      "react-template-rr": [
        {
          "file": "apps/react-template-rr/.env.sample",
          "hash": "2860593346788357752"
        },
        {
          "file": "apps/react-template-rr/.eslintrc.cjs",
          "hash": "15898001655895264066"
        },
        {
          "file": "apps/react-template-rr/.github/issue_template.md",
          "hash": "10395249463968647000"
        },
        {
          "file": "apps/react-template-rr/.github/pull_request_template.md",
          "hash": "17709958282604071433"
        },
        {
          "file": "apps/react-template-rr/.github/workflows/ci_cd.yml",
          "hash": "5878850679542105345"
        },
        {
          "file": "apps/react-template-rr/.github/workflows/dependencies_update.yml",
          "hash": "16553150589125657534"
        },
        {
          "file": "apps/react-template-rr/.gitignore",
          "hash": "14017190595697113011"
        },
        {
          "file": "apps/react-template-rr/.husky/pre-commit",
          "hash": "2832096641533408145"
        },
        {
          "file": "apps/react-template-rr/.lintstagedrc.cjs",
          "hash": "84872462262408638"
        },
        {
          "file": "apps/react-template-rr/.prettierrc.cjs",
          "hash": "15972565883177503442",
          "deps": [
            "prettier-config"
          ]
        },
        {
          "file": "apps/react-template-rr/LICENSE.md",
          "hash": "9160496680738198191"
        },
        {
          "file": "apps/react-template-rr/README.md",
          "hash": "12541862783469366744"
        },
        {
          "file": "apps/react-template-rr/README.png",
          "hash": "14297219811092734781"
        },
        {
          "file": "apps/react-template-rr/app/app.css",
          "hash": "5541517512288623449"
        },
        {
          "file": "apps/react-template-rr/app/components/theme-provider.tsx",
          "hash": "5514393571956280194",
          "deps": [
            "npm:react@19.1.0"
          ]
        },
        {
          "file": "apps/react-template-rr/app/components/theme-switch/theme-switch.tsx",
          "hash": "2369849427968347846",
          "deps": [
            "npm:lucide-react@0.507.0",
            "npm:react@19.1.0"
          ]
        },
        {
          "file": "apps/react-template-rr/app/components/viewport-info/viewport-info.tsx",
          "hash": "17000261910949605161",
          "deps": [
            "npm:lucide-react@0.507.0",
            "npm:react@19.1.0"
          ]
        },
        {
          "file": "apps/react-template-rr/app/lib/hooks/useHealthcheck.ts",
          "hash": "12898702526557285818",
          "deps": [
            "npm:@tanstack/react-query"
          ]
        },
        {
          "file": "apps/react-template-rr/app/lib/misc/react-query.ts",
          "hash": "3244421341483603138"
        },
        {
          "file": "apps/react-template-rr/app/lib/mocks/browser.ts",
          "hash": "16407634322328369340",
          "deps": [
            "npm:msw"
          ]
        },
        {
          "file": "apps/react-template-rr/app/lib/mocks/handlers.ts",
          "hash": "17484102537343688284",
          "deps": [
            "npm:msw"
          ]
        },
        {
          "file": "apps/react-template-rr/app/lib/mocks/index.ts",
          "hash": "3244421341483603138"
        },
        {
          "file": "apps/react-template-rr/app/lib/mocks/node.ts",
          "hash": "11959845792427069976",
          "deps": [
            "npm:msw"
          ]
        },
        {
          "file": "apps/react-template-rr/app/root.tsx",
          "hash": "18137731222170294069",
          "deps": [
            "npm:@tanstack/react-query",
            "npm:@tanstack/react-query-devtools",
            "npm:lucide-react@0.507.0",
            "npm:react@19.1.0",
            "npm:react-router"
          ]
        },
        {
          "file": "apps/react-template-rr/app/routes.ts",
          "hash": "9511869395424924952",
          "deps": [
            "npm:@react-router/dev"
          ]
        },
        {
          "file": "apps/react-template-rr/app/routes/index.tsx",
          "hash": "10769227860048872094",
          "deps": [
            "npm:lucide-react@0.507.0"
          ]
        },
        {
          "file": "apps/react-template-rr/e2e/index.spec.ts",
          "hash": "4222966287012883104",
          "deps": [
            "npm:@playwright/test"
          ]
        },
        {
          "file": "apps/react-template-rr/eslint.config.mjs",
          "hash": "6334162303930344531",
          "deps": [
            "npm:@eslint/compat",
            "npm:@eslint/eslintrc",
            "npm:@eslint/js@9.28.0",
            "npm:@typescript-eslint/eslint-plugin",
            "npm:eslint-plugin-import",
            "npm:eslint-plugin-jest",
            "npm:eslint-plugin-jsx-a11y",
            "npm:eslint-plugin-playwright",
            "npm:eslint-plugin-react",
            "npm:eslint-plugin-react-hooks",
            "npm:eslint-plugin-testing-library",
            "npm:globals@16.2.0",
            "eslint-config"
          ]
        },
        {
          "file": "apps/react-template-rr/jest.config.cjs",
          "hash": "13894586402330565312"
        },
        {
          "file": "apps/react-template-rr/jest.setup.cjs",
          "hash": "6522525646068463988",
          "deps": [
            "npm:@testing-library/jest-dom"
          ]
        },
        {
          "file": "apps/react-template-rr/package.json",
          "hash": "5308148841885382014",
          "deps": [
            "npm:@eslint/compat",
            "npm:@eslint/eslintrc",
            "npm:@eslint/js@9.28.0",
            "eslint-config",
            "prettier-config",
            "tsconfig",
            "npm:@playwright/test",
            "npm:@react-router/dev",
            "npm:@tailwindcss/postcss",
            "npm:@testing-library/dom",
            "npm:@testing-library/jest-dom",
            "npm:@testing-library/react",
            "npm:@testing-library/user-event",
            "npm:@types/jest",
            "npm:@types/node",
            "npm:@types/react",
            "npm:@types/react-dom",
            "npm:@typescript-eslint/eslint-plugin",
            "npm:@typescript-eslint/parser",
            "npm:@vitejs/plugin-react",
            "npm:concurrently",
            "npm:eslint@9.26.0",
            "npm:eslint-config-prettier",
            "npm:eslint-import-resolver-typescript@4.4.3",
            "npm:eslint-plugin-import",
            "npm:eslint-plugin-jest",
            "npm:eslint-plugin-jsx-a11y",
            "npm:eslint-plugin-playwright",
            "npm:eslint-plugin-prettier",
            "npm:eslint-plugin-react",
            "npm:eslint-plugin-react-hooks",
            "npm:eslint-plugin-tailwindcss",
            "npm:eslint-plugin-testing-library",
            "npm:globals@16.2.0",
            "npm:husky",
            "npm:jest",
            "npm:jest-environment-jsdom",
            "npm:lint-staged@15.5.2",
            "npm:msw",
            "npm:postcss@8.5.4",
            "npm:prettier@3.5.3",
            "npm:tailwindcss",
            "npm:ts-node",
            "npm:typescript",
            "npm:vite",
            "npm:vite-plugin-eslint",
            "npm:vite-tsconfig-paths",
            "npm:@react-router/node",
            "npm:@react-router/serve",
            "npm:@tanstack/react-query",
            "npm:@tanstack/react-query-devtools",
            "npm:clsx",
            "npm:isbot",
            "npm:lucide-react@0.507.0",
            "npm:react@19.1.0",
            "npm:react-dom@19.1.0",
            "npm:react-router"
          ]
        },
        {
          "file": "apps/react-template-rr/playwright.config.ts",
          "hash": "2377917740166769640",
          "deps": [
            "npm:@playwright/test"
          ]
        },
        {
          "file": "apps/react-template-rr/pnpm-lock.yaml",
          "hash": "1401968907405015416"
        },
        {
          "file": "apps/react-template-rr/postcss.config.js",
          "hash": "3353885786474150661"
        },
        {
          "file": "apps/react-template-rr/project.json",
          "hash": "10826372058126408269"
        },
        {
          "file": "apps/react-template-rr/public/favicon.ico",
          "hash": "4262445438011821815"
        },
        {
          "file": "apps/react-template-rr/public/mockServiceWorker.js",
          "hash": "490194639004359583"
        },
        {
          "file": "apps/react-template-rr/react-router.config.ts",
          "hash": "13157102690616087801",
          "deps": [
            "npm:@react-router/dev"
          ]
        },
        {
          "file": "apps/react-template-rr/tsconfig.json",
          "hash": "3533197393151183469"
        },
        {
          "file": "apps/react-template-rr/vercel.json",
          "hash": "15535816575235842323"
        },
        {
          "file": "apps/react-template-rr/vite-env.d.ts",
          "hash": "12946363841406869089"
        },
        {
          "file": "apps/react-template-rr/vite.config.ts",
          "hash": "9175825519291434935",
          "deps": [
            "npm:@react-router/dev",
            "npm:vite",
            "npm:vite-plugin-eslint",
            "npm:vite-tsconfig-paths"
          ]
        }
      ]
    },
    "nonProjectFiles": [
      {
        "file": "nx.json",
        "hash": "14785521543697147829"
      },
      {
        "file": "package.json",
        "hash": "14430366140042638455"
      },
      {
        "file": "pnpm-lock.yaml",
        "hash": "4551864492809883565"
      },
      {
        "file": "pnpm-workspace.yaml",
        "hash": "9750177317466281158"
      },
      {
        "file": "tsconfig.base.json",
        "hash": "17072856088031261049"
      }
    ]
  }
}